cli/__init__.py
cli/cli.py
neuragens_cli-1.0.1.dist-info/LICENSE
neuragens_cli-1.0.1.dist-info/METADATA
neuragens_cli-1.0.1.dist-info/WHEEL
neuragens_cli-1.0.1.dist-info/entry_points.txt
neuragens_cli-1.0.1.dist-info/top_level.txt
neuragens_cli-1.0.1.dist-info/RECORD
